{
  "settings": {
    "migrated": 4,
    "iconPacksPath": ".obsidian/icons",
    "fontSize": 16,
    "emojiStyle": "none",
    "iconColor": "#8a5cf5",
    "recentlyUsedIcons": [
      "LiDivideSquare",
      "SiSpring",
      "SiWolfram",
      "FasB",
      "FasD",
      "RiStarHalfFill",
      "TiBoxModel",
      "RiLockPasswordLine",
      "SiRust",
      "SiLinux",
      "TiCloudNetwork",
      "FasComputer",
      "SiAssemblyscript",
      "SiAltiumdesigner",
      "RiAttachmentLine",
      "SiOpenproject",
      "SiPolymerproject",
      "FasDiagramProject",
      "SiTestcafe",
      "IbDocumentText",
      "RiAttachment2",
      "TiJetpack",
      "SiGooglecontaineroptimizedos",
      "LiLibrary",
      "TiArrowsDoubleSwNe"
    ],
    "recentlyUsedIconsSize": 25,
    "rules": [],
    "extraMargin": {
      "top": 0,
      "right": 4,
      "bottom": 0,
      "left": 0
    },
    "iconInTabsEnabled": false,
    "iconInTitleEnabled": false,
    "iconInFrontmatterEnabled": false,
    "iconsBackgroundCheckEnabled": false,
    "iconsInNotesEnabled": true,
    "iconIdentifier": ":"
  },
  "笔记/计算机网络": "TiNetwork",
  "笔记/其他": "TiBraces",
  "笔记": "RiSparklingLine",
  "笔记/设计模式": "SiMaterialdesign",
  "笔记/数据库": "TiDatabase",
  "笔记/设计模式/构建型模式 Creational Patterns": "SiBuildkite",
  "笔记/设计模式/结构型模式 Structural Patterns": "SiInstructure",
  "笔记/设计模式/行为型模式 Behavioral Patterns": "SiInteractiondesignfoundation",
  "笔记/算法与数据结构": "TiCode",
  "笔记/算法与数据结构/理论": "SiKnowledgebase",
  "笔记/算法与数据结构/算法": "SiCodemagic",
  "笔记/算法与数据结构/题目收藏": "RiQuestionFill",
  "笔记/算法与数据结构/题目收藏/数据结构": "SiDatadotai",
  "笔记/算法与数据结构/题目收藏/数据结构/优先队列": "LiArrowUpSquare",
  "笔记/算法与数据结构/题目收藏/数据结构/链表": "RaChain",
  "笔记/算法与数据结构/题目收藏/数据结构/队列": "CoAddToQueue",
  "笔记/算法与数据结构/题目收藏/数据结构/数组": "FiList",
  "笔记/算法与数据结构/题目收藏/数据结构/双端队列": "IbArrowSwitch",
  "笔记/算法与数据结构/题目收藏/数据结构/哈希表": "FiHash",
  "笔记/算法与数据结构/题目收藏/数据结构/树": "TiBinaryTree",
  "笔记/算法与数据结构/题目收藏/数据结构/栈": "RiStackFill",
  "笔记/算法与数据结构/题目收藏/数据结构/字符串": "TiQuotes",
  "笔记/算法与数据结构/题目收藏/算法": "SiCodeforces",
  "笔记/算法与数据结构/算法/排序算法": "TiSort09",
  "笔记/算法与数据结构/题目收藏/题库": "LiLibrary",
  "笔记/优化算法": "SiGooglecontaineroptimizedos",
  "笔记/Jetpack Compose": "TiJetpack",
  "附件": "RiAttachment2",
  "归档": "IbDocumentText",
  "归档/考研": "SiTestcafe",
  "项目": "SiOpenproject",
  "asset": "RiAttachmentLine",
  "项目/毕设": "SiAltiumdesigner",
  "项目/汇编与接口技术课程设计": "SiAssemblyscript",
  "项目/计算机组成原理课程设计": "FasComputer",
  "项目/网络安全": "TiCloudNetwork",
  "笔记/算法与数据结构/题目收藏/算法/递归": "SiLoop",
  "笔记/算法与数据结构/题目收藏/算法/双指针": "TiArrowsDoubleSwNe",
  "项目/毕设/rCore": "SiLinux",
  "项目/毕设/RUST": "SiRust",
  "项目/加密传输": "RiLockPasswordLine",
  "附件/模板": "TiBoxModel",
  "笔记/算法与数据结构/题目收藏/算法/二分查找": "RiStarHalfFill",
  "笔记/算法与数据结构/题目收藏/算法/深度优先搜索": "FasD",
  "笔记/算法与数据结构/题目收藏/算法/广度优先搜索": "FasB",
  "笔记/算法与数据结构/题目收藏/算法/数学": "SiWolfram",
  "笔记/SpringBoot": "SiSpring",
  "笔记/算法与数据结构/题目收藏/算法/分治": "LiDivideSquare"
}